huaweicloudsdkiotanalytics/__init__.py
huaweicloudsdkiotanalytics/v1/__init__.py
huaweicloudsdkiotanalytics/v1/iotanalytics_async_client.py
huaweicloudsdkiotanalytics/v1/iotanalytics_client.py
huaweicloudsdkiotanalytics/v1/model/__init__.py
huaweicloudsdkiotanalytics/v1/model/add_dev_data_request.py
huaweicloudsdkiotanalytics/v1/model/add_dev_data_response.py
huaweicloudsdkiotanalytics/v1/model/add_pipeline_job_request.py
huaweicloudsdkiotanalytics/v1/model/add_pipeline_job_response.py
huaweicloudsdkiotanalytics/v1/model/aggregate_metric.py
huaweicloudsdkiotanalytics/v1/model/aggregate_metrics.py
huaweicloudsdkiotanalytics/v1/model/aggregate_metrics_request.py
huaweicloudsdkiotanalytics/v1/model/aggregate_model.py
huaweicloudsdkiotanalytics/v1/model/aggregate_response.py
huaweicloudsdkiotanalytics/v1/model/analysis_model_request.py
huaweicloudsdkiotanalytics/v1/model/analysis_model_response.py
huaweicloudsdkiotanalytics/v1/model/analysis_request.py
huaweicloudsdkiotanalytics/v1/model/analysis_response.py
huaweicloudsdkiotanalytics/v1/model/api_content_req.py
huaweicloudsdkiotanalytics/v1/model/api_content_rsp.py
huaweicloudsdkiotanalytics/v1/model/asset_add_request.py
huaweicloudsdkiotanalytics/v1/model/asset_mod_request.py
huaweicloudsdkiotanalytics/v1/model/asset_model_add_request.py
huaweicloudsdkiotanalytics/v1/model/asset_model_mod_request.py
huaweicloudsdkiotanalytics/v1/model/asset_model_response.py
huaweicloudsdkiotanalytics/v1/model/asset_property_last_value.py
huaweicloudsdkiotanalytics/v1/model/asset_response.py
huaweicloudsdkiotanalytics/v1/model/column.py
huaweicloudsdkiotanalytics/v1/model/computing_resource.py
huaweicloudsdkiotanalytics/v1/model/content_detail_req.py
huaweicloudsdkiotanalytics/v1/model/content_detail_rsp.py
huaweicloudsdkiotanalytics/v1/model/create_asset_model_request.py
huaweicloudsdkiotanalytics/v1/model/create_asset_model_response.py
huaweicloudsdkiotanalytics/v1/model/create_asset_new_request.py
huaweicloudsdkiotanalytics-3.1.184.dist-info/METADATA
huaweicloudsdkiotanalytics-3.1.184.dist-info/WHEEL
huaweicloudsdkiotanalytics-3.1.184.dist-info/licenses/LICENSE
huaweicloudsdkiotanalytics-3.1.184.dist-info/RECORD
